{
  "Alessandro Oliveira": {
    "perfil": "Efetivo",
    "time": "A definir"
  },
  "Andre Novaes": {
    "perfil": "Efetivo",
    "time": "A definir"
  },
  "Bruno Loschi": {
    "perfil": "Efetivo",
    "time": "A definir"
  },
  "Felipe Vieira da Silva": {
    "perfil": "Efetivo",
    "time": "A definir"
  },
  "Gabriel Abramo": {
    "perfil": "Efetivo",
    "time": "A definir"
  },
  "Guilherme dos Santos Ramos": {
    "perfil": "Efetivo",
    "time": "A definir"
  },
  "Gustavo Kowalski": {
    "perfil": "Efetivo",
    "time": "A definir"
  },
  "Gustavo Silva": {
    "perfil": "Efetivo",
    "time": "A definir"
  },
  "Iago Lucas Fernandes de Faria": {
    "perfil": "Efetivo",
    "time": "A definir"
  },
  "Jefferson Silva": {
    "perfil": "Efetivo",
    "time": "A definir"
  },
  "João Felipe Bertini": {
    "perfil": "Efetivo",
    "time": "A definir"
  },
  "Kayke Peres da Costa": {
    "perfil": "Efetivo",
    "time": "A definir"
  },
  "Kayky Stiliano": {
    "perfil": "Efetivo",
    "time": "A definir"
  },
  "Leonardo Miranda": {
    "perfil": "Efetivo",
    "time": "A definir"
  },
  "Luany Avila dos Anjos": {
    "perfil": "Efetivo",
    "time": "A definir"
  },
  "Lucas Ortiz": {
    "perfil": "Efetivo",
    "time": "A definir"
  },
  "Lucas Torino": {
    "perfil": "Efetivo",
    "time": "A definir"
  },
  "Matheus Angelo": {
    "perfil": "Efetivo",
    "time": "A definir"
  },
  "Matheus Nascimento": {
    "perfil": "Efetivo",
    "time": "A definir"
  },
  "Nattan Souza": {
    "perfil": "Efetivo",
    "time": "A definir"
  },
  "Vinicius Rodrigues dos Santos": {
    "perfil": "Efetivo",
    "time": "A definir"
  },
  "Vitor da Silva Sant'ana": {
    "perfil": "Efetivo",
    "time": "A definir"
  }
}